resmda/__init__.py
resmda/data_assimilation.py
resmda/reservoir_simulator.py
resmda/utils.py
resmda/version.py
resmda-1.0.2.dist-info/LICENSE
resmda-1.0.2.dist-info/METADATA
resmda-1.0.2.dist-info/WHEEL
resmda-1.0.2.dist-info/top_level.txt
resmda-1.0.2.dist-info/RECORD
