Metadata-Version: 2.1
Name: resmda
Version: 1.0.2
Summary: ES-MDA with a simple 2D reservoir modeller
Author: Gabriel Serrao Seabra, Femke C. Vossepoel
Author-email: Dieter Werthmüller <info@emsig.xyz>
License:                                  Apache License
Project-URL: Homepage, https://tuda-geo.github.io/resmda
Project-URL: Documentation, https://tuda-geo.github.io/resmda
Project-URL: Repository, https://github.com/tuda-geo/resmda
Classifier: Development Status :: 5 - Production/Stable
Classifier: License :: OSI Approved :: Apache Software License
Classifier: Programming Language :: Python
Requires-Python: >=3.10
License-File: LICENSE
Requires-Dist: numpy
Requires-Dist: scipy>=1.10
Requires-Dist: scooby
Provides-Extra: docs
Requires-Dist: pooch; extra == "docs"
Requires-Dist: ipympl; extra == "docs"
Requires-Dist: sphinx>=7.3; extra == "docs"
Requires-Dist: numpydoc; extra == "docs"
Requires-Dist: ipykernel; extra == "docs"
Requires-Dist: matplotlib; extra == "docs"
Requires-Dist: pickleshare; extra == "docs"
Requires-Dist: sphinx_design; extra == "docs"
Requires-Dist: sphinx_numfig; extra == "docs"
Requires-Dist: sphinx_gallery>=0.16; extra == "docs"
Requires-Dist: memory_profiler; extra == "docs"
Requires-Dist: sphinx_automodapi; extra == "docs"
Requires-Dist: pydata_sphinx_theme; extra == "docs"
Provides-Extra: tests
Requires-Dist: flake8; extra == "tests"
Requires-Dist: pytest; extra == "tests"
Requires-Dist: coveralls; extra == "tests"
Requires-Dist: pytest_cov; extra == "tests"
Requires-Dist: flake8-pyproject; extra == "tests"
Provides-Extra: all
Requires-Dist: resmda[docs]; extra == "all"
Requires-Dist: resmda[tests]; extra == "all"
Provides-Extra: build
Requires-Dist: setuptools_scm>=8; extra == "build"
Requires-Dist: setuptools>=64; extra == "build"
